README.md
XCaliburMethodReader.py
setup.cfg
setup.py
XCaliburMethodReader.egg-info/PKG-INFO
XCaliburMethodReader.egg-info/SOURCES.txt
XCaliburMethodReader.egg-info/dependency_links.txt
XCaliburMethodReader.egg-info/entry_points.txt
XCaliburMethodReader.egg-info/requires.txt
XCaliburMethodReader.egg-info/top_level.txt